chartilo/__init__.py
chartilo/chartilo.py
chartilo/drawers/__init__.py
chartilo/drawers/candleChartDrawer.py
chartilo/drawers/drawer.py
chartilo/drawers/gridDrawer.py
chartilo/drawers/lineChartDrawer.py
chartilo/drawers/lineDrawer.py
chartilo/drawers/maxMinValuesDrawer.py
chartilo/factories/__init__.py
chartilo/factories/vertexesFactory.py
chartilo/models/__init__.py
chartilo/models/candle.py
chartilo/models/line.py
chartilo/positioners/__init__.py
chartilo/positioners/chartPositioner.py
chartilo/positioners/limiter.py
chartilo/themes/__init__.py
chartilo/themes/dark.py
chartilo/themes/light.py
chartilo/themes/theme.py
chartilo/themes/themeHolder.py
chartilo-0.0.3.dist-info/LICENSE
chartilo-0.0.3.dist-info/METADATA
chartilo-0.0.3.dist-info/WHEEL
chartilo-0.0.3.dist-info/top_level.txt
chartilo-0.0.3.dist-info/RECORD
