Metadata-Version: 2.1
Name: chartilo
Version: 0.0.3
Summary: Streaming video data via networks
Home-page: UNKNOWN
Author: Moryakov Vladislav
Author-email: <vlad_moryakov_prog@mail.ru>
License: UNKNOWN
Keywords: chart,python,candle
Platform: UNKNOWN
Classifier: Development Status :: 1 - Planning
Classifier: Intended Audience :: Developers
Classifier: Programming Language :: Python :: 3
Classifier: Operating System :: Unix
Classifier: Operating System :: MacOS :: MacOS X
Classifier: Operating System :: Microsoft :: Windows
License-File: LICENSE
Requires-Dist: pyqt5
